tsib/__init__.py
tsib/buildingconfig.py
tsib/buildingmodel.py
tsib/data/__init__.py
tsib/data/__pycache__/__init__.cpython-37.pyc
tsib/data/costdata/default_2016.xlsx
tsib/data/episcope/episcope.csv
tsib/data/episcope/source.txt
tsib/data/episcope/tabula_DE_wPersons.csv
tsib/data/results/.gitignore
tsib/data/results/buildingprofiles/.gitignore
tsib/data/results/buildingstaticresults/.gitignore
tsib/data/results/fireplaceprofiles/.gitignore
tsib/data/results/occupantprofiles/.gitignore
tsib/data/sandia/inverters/sandia_modules.csv
tsib/data/sandia/pvmodules/sandia_modules.csv
tsib/data/weatherdata/ISO12831/NormTemperature_ISO_12831.txt
tsib/data/weatherdata/ISO12831/T_processed.csv
tsib/data/weatherdata/ISO12831/T_zones_Ger_final.csv
tsib/data/weatherdata/ISO12831/TransformTable.ipynb
tsib/data/weatherdata/ISO12831/Untitled.ipynb
tsib/data/weatherdata/TMY/Germany DEU Koln (INTL).csv
tsib/data/weatherdata/TRY/.gitignore
tsib/data/weatherdata/TRY/TRY2010_01_Jahr.dat
tsib/data/weatherdata/TRY/TRY2010_02_Jahr.csv
tsib/data/weatherdata/TRY/TRY2010_02_Jahr.dat
tsib/data/weatherdata/TRY/TRY2010_03_Jahr.dat
tsib/data/weatherdata/TRY/TRY2010_04_Jahr.csv
tsib/data/weatherdata/TRY/TRY2010_04_Jahr.dat
tsib/data/weatherdata/TRY/TRY2010_05_Jahr.csv
tsib/data/weatherdata/TRY/TRY2010_05_Jahr.dat
tsib/data/weatherdata/TRY/TRY2010_06_Jahr.csv
tsib/data/weatherdata/TRY/TRY2010_06_Jahr.dat
tsib/data/weatherdata/TRY/TRY2010_07_Jahr.dat
tsib/data/weatherdata/TRY/TRY2010_08_Jahr.dat
tsib/data/weatherdata/TRY/TRY2010_09_Jahr.dat
tsib/data/weatherdata/TRY/TRY2010_10_Jahr.dat
tsib/data/weatherdata/TRY/TRY2010_11_Jahr.dat
tsib/data/weatherdata/TRY/TRY2010_12_Jahr.csv
tsib/data/weatherdata/TRY/TRY2010_12_Jahr.dat
tsib/data/weatherdata/TRY/TRY2010_13_Jahr.csv
tsib/data/weatherdata/TRY/TRY2010_13_Jahr.dat
tsib/data/weatherdata/TRY/TRY2010_14_Jahr.dat
tsib/data/weatherdata/TRY/TRY2010_15_Jahr.dat
tsib/household/__init__.py
tsib/household/profiles.py
tsib/renewables/__init__.py
tsib-0.1.4.dist-info/METADATA
tsib-0.1.4.dist-info/WHEEL
tsib-0.1.4.dist-info/top_level.txt
tsib-0.1.4.dist-info/RECORD
