Metadata-Version: 2.1
Name: tsib
Version: 0.1.4
Summary: Time Series Initialization for Buildings
Home-page: https://github.com/FZJ-IEK3-VSA/tsib
Author: Leander Kotzur
Author-email: l.kotzur@fz-juelich.de
Keywords: buildings,thermal load,electricity load,optimization
Classifier: Development Status :: 4 - Beta
Classifier: Intended Audience :: End Users/Desktop
Classifier: Intended Audience :: Science/Research
Classifier: License :: OSI Approved :: MIT License
Classifier: Natural Language :: English
Classifier: Operating System :: OS Independent
Classifier: Programming Language :: Python
Classifier: Programming Language :: Python :: 2
Classifier: Programming Language :: Python :: 2.7
Classifier: Programming Language :: Python :: 3
Classifier: Programming Language :: Python :: 3.4
Classifier: Programming Language :: Python :: 3.5
Classifier: Programming Language :: Python :: 3.6
Classifier: Topic :: Scientific/Engineering
Classifier: Topic :: Software Development :: Libraries :: Python Modules
Requires-Dist: pvlib (>=0.7.0)
Requires-Dist: pandas (>=0.24.0)
Requires-Dist: Pyomo (>=4.2)
Requires-Dist: numpy
Requires-Dist: matplotlib (>=3.0.0)
Requires-Dist: xlrd
Requires-Dist: tsam (>=1.0.4)
Requires-Dist: tsorb
Requires-Dist: cdsapi
Requires-Dist: tinydb
